{
  "field_name": "Предкарпатье (по умолчанию)",
  "well_selection": {
    "m_pr_min": 7,
    "m_pr_max": 11,
    "m_pr_default": 8,
    "h_pr_min": 5,
    "C_k_pr": 3,
    "C_gl_pr": 10,
    "k_g_np": 1.1,
    "q_pr": 24
  },
  "reaction_kinetics": {
    "alpha_kgo": 0.1,
    "comment_alpha": "Коэффициент в формуле kг.о = exp(-α·r). Для Предкарпатья = 0.1"
  },
  "rock_properties": {
    "rho_sk_min": 2600,
    "rho_sk_max": 2700,
    "rho_sk_default": 2650,
    "rho_p_min": 2200,
    "rho_p_max": 2300,
    "rho_p_default": 2300,
    "k_mg_min": 1.1,
    "k_mg_max": 1.3,
    "k_mg_default": 1.2,
    "R_mg_min": 1.5e-5,
    "R_mg_max": 2.2e-5,
    "R_mg_default": 1.8e-5
  },
  "dissolution_coefficients": {
    "comment": "Растворимость породы в ГКР: DG_g = a_gl·C_гл + b_k·C_к (HF растворяет глины/алюмосиликаты)",
    "a_gl_clay": 0.6,
    "b_k_carbonate": 0.3,
    "a_clay_skr": 0.25,
    "b_carbonate_skr": 0.5
  },
  "permeability_regressions": {
    "comment": "k_0 = A * m_0^B (мкм²) — регрессии Будзеня (Предкарпатье)",
    "KL_1": {"A": 1.632e-7,  "B": 4.74},
    "KL_2": {"A": 1.278e-9,  "B": 6.34},
    "KL_3": {"A": 1.587e-9,  "B": 5.92},
    "KL_4": {"A": 7.65e-10,  "B": 5.85},
    "KL_5": {"A": 7.43e-12,  "B": 7.62}
  },
  "permeability_change_after_sko": {
    "comment": "k_s* = A * exp(B * C_к) (В.44)",
    "A": 0.9,
    "B": 0.2
  },
  "hf_diffusion_table": {
    "comment": "Таблица В.20 — коэффициент диффузии HF D_г (·1e-9 м²/с) при 20 °C по концентрации HF, %",
    "rows": [
      {"C_HF": 1, "D_g": 2.30},
      {"C_HF": 2, "D_g": 2.42},
      {"C_HF": 3, "D_g": 2.55},
      {"C_HF": 4, "D_g": 2.66},
      {"C_HF": 5, "D_g": 2.74}
    ]
  },
  "n_ko_table": {
    "comment": "Таблица В.15 — число обработок ГКО N_ко и подбор y (% HF) по карбонатности",
    "rows": [
      {"C_k_max": 3,  "y_by_Nko": [1, 2, 2, 3, 3, 3]},
      {"C_k_max": 5,  "y_by_Nko": [0, 0, 1, 2, 3, 3]},
      {"C_k_max": 999,"y_by_Nko": [0, 0, 0, 1, 2, 3]}
    ]
  },
  "collector_types": {
    "comment": "Таблица В.10 — типизация пород-коллекторов",
    "KL_1": {"name": "Песчаники среднемелкозернистые", "cement": "<5%", "clay": 2, "k_uf": 0.42},
    "KL_2": {"name": "Песчаники мелкозернистые", "cement": "<5%", "clay": 3, "k_uf": 0.37},
    "KL_3": {"name": "Песчаники мелкозернистые, глинизированные", "cement": "5-10%", "clay": 8, "k_uf": 0.32},
    "KL_4": {"name": "Песчаники мелкозернистые, алевролиты", "cement": "10-20%", "clay": 8, "k_uf": 0.26},
    "KL_5": {"name": "Алевролиты слабоглинизированные", "cement": "<10%", "clay": 5, "k_uf": 0.23}
  }
}
